<?xml version="1.0" encoding="euc-kr" standalone="no"?>
<!DOCTYPE superEntry SYSTEM "vv.dtd">
<superEntry>
	<orth>농성하다</orth>
	<entry pos="vv">
		<mnt_grp>
			<cre>
				<cre_date>2005/07/01</cre_date>
				<cre_writer>김선영</cre_writer>
			</cre>
			<mod>
				<mod_date>2006/09/30</mod_date>
				<mod_writer>김민선</mod_writer>
				<mod_note>어휘의미관계 보충</mod_note>
			</mod>
		</mnt_grp>
		<morph_grp>
			<var type="spr">농성을 하다</var>
			<str>N.하</str>
			<org lg="si">籠城_</org>
		</morph_grp>
		<sense>
			<sem_grp>
				<sem_class>지속적활동</sem_class>
				<trans>hold a castle</trans>
				<lr>
					<syn type="perfect">수성하다</syn>
					<hyper>지키다</hyper>
				</lr>
			</sem_grp>
			<frame_grp type="FIN">
				<frame>X=N0-이 V</frame>
				<subsense>
					<sel_rst arg="X" tht="AGT">인간|인간집단</sel_rst>
					<eg>영화에서 용사들이 농성하는 장면이 기억에 남는다.</eg>
				</subsense>
			</frame_grp>
		</sense>
		<sense>
			<sem_grp>
				<sem_class>소통행위</sem_class>
				<trans>stage a sit-down demonstration</trans>
				<lr>
					<syn type="perfect">시위하다</syn>
				</lr>
			</sem_grp>
			<frame_grp type="FIN">
				<frame>X=N0-이 Y=N1-에서 Z=S2-고 V</frame>
				<subsense>
					<sel_rst arg="X" tht="AGT">인간|인간집단</sel_rst>
					<sel_rst arg="Y" tht="LOC">장소</sel_rst>
					<sel_rst arg="Z" tht="CNT"></sel_rst>
					<eg>공장에서는 근로자 14명이 밀린 임금과 퇴직금을 돌려달라고 농성하고 있다.</eg>
				</subsense>
			</frame_grp>
			<frame_grp type="FIN">
				<frame>X=N0-이 Y=N2-에서 Z=N1-을위해 V</frame>
				<subsense>
					<sel_rst arg="X" tht="AGT">인간|인간집단</sel_rst>
					<sel_rst arg="Y" tht="LOC">장소</sel_rst>
					<sel_rst arg="Z" tht="THM">행위(임금인상|석방|고용안정)</sel_rst>
					<eg>공장에서는 근로자 14명이 검거된 노조원의 석방을 위해 농성하고 있다.</eg>
				</subsense>
			</frame_grp>
		</sense>
	</entry>
</superEntry>
