<?xml version="1.0" encoding="euc-kr" standalone="no"?>
<!DOCTYPE superEntry SYSTEM "vv.dtd">
<superEntry>
	<orth>서방질하다</orth>
	<entry pos="vv">
		<mnt_grp>
			<cre>
				<cre_date>2005/07/12</cre_date>
				<cre_writer>안소진</cre_writer>
			</cre>
			<mod>
				<mod_date>2006/07/28</mod_date>
				<mod_writer>안소진</mod_writer>
			</mod>
			<mod>
				<mod_date></mod_date>
				<mod_writer></mod_writer>
			</mod>
		</mnt_grp>
		<morph_grp>
			<var type="spr">서방질을 하다</var>
			<str>N.하</str>
			<org lg="si">書房__</org>
		</morph_grp>
		<sense>
			<sem_grp>
				<sem_class>결과행위</sem_class>
				<trans>cuckold</trans>
				<trans>commit adultery</trans>
			</sem_grp>
			<frame_grp type="FIN">
				<frame>X=N0-이 V</frame>
				<subsense>
					<sel_rst arg="X" tht="AGT">여성인간</sel_rst>
					<eg>남편은 서방질하는 아내를 눈감아 주었다.</eg>
					<eg></eg>
				</subsense>
			</frame_grp>
		</sense>
	</entry>
</superEntry>
