<?xml version="1.0" encoding="euc-kr" standalone="no"?>
<!DOCTYPE superEntry SYSTEM "vv.dtd">
<superEntry>
	<orth>우물거리다</orth>
	<entry n="1" pos="vv">
		<mnt_grp>
			<cre>
				<cre_date>2002/06/15</cre_date>
				<cre_writer>노윤채</cre_writer>
			</cre>
			<mod>
				<mod_date>2002/10/14</mod_date>
				<mod_writer>김종명</mod_writer>
			</mod>
			<mod>
				<mod_date>2003/07/18</mod_date>
				<mod_writer>노윤채</mod_writer>
			</mod>
			<mod>
				<mod_date>2004/12/16</mod_date>
				<mod_writer>한선혜</mod_writer>
			</mod>
		</mnt_grp>
		<morph_grp>
			<var type="etc">오물거리다</var>
			<cntr opt="obl" type="i"/>
			<str>I.거</str>
			<infl type="reg"/>
		</morph_grp>
		<sense>
			<sem_grp>
				<sem_class>반복적행위</sem_class>
				<trans>mumble</trans>
			</sem_grp>
			<frame_grp type="FTR" cor="nut" n="01">
				<frame>X=N0-이 Y=N1-을 V</frame>
				<subsense>
					<sel_rst arg="X" tht="AGT">인간</sel_rst>
					<sel_rst arg="Y" tht="THM">(입|입술)</sel_rst>
					<eg>아이는 무슨 말을 하려는 듯 입술을 우물거렸으나 아무도 그 말을 알아들을 수 없었다.</eg>
				</subsense>
			</frame_grp>
		</sense>
		<sense>
			<sem_grp>
				<sem_class>반복적행위</sem_class>
				<trans>chew sth with one's mouth closed</trans>
			</sem_grp>
			<frame_grp type="FTR">
				<frame>X=N0-이 Y=N1-을 V</frame>
				<subsense>
					<sel_rst arg="X" tht="AGT">인간</sel_rst>
					<sel_rst arg="Y" tht="THM">음식</sel_rst>
					<eg>아저씨는 밥을 한 수저 푹 떠서 입안 가득 넣으며 우물거린다.</eg>
					<eg>늘 하품하며 우물거리는 암소와 엄마를 떠나지 못하는 어린 송아지의 정 나누는 모습 외에는 인기척을 찾을 수 없었다.</eg>
				</subsense>
			</frame_grp>
		</sense>
		<sense>
			<sem_grp>
				<sem_class>반복적행위</sem_class>
				<trans>speak haltingly</trans>
			</sem_grp>
			<frame_grp type="FTR">
				<frame>X=N0-이 Y=N1-을 V</frame>
				<subsense>
					<sel_rst arg="X" tht="AGT">인간</sel_rst>
					<sel_rst arg="Y" tht="THM">(말)</sel_rst>
					<eg>그렇게 말을 입 속에서 우물거리지 말고 시원스럽게 해 봐.</eg>
				</subsense>
			</frame_grp>
		</sense>
		<sense>
			<sem_grp>
				<sem_class>반복적행위</sem_class>
				<trans>mumble</trans>
			</sem_grp>
			<frame_grp type="FIN" cor="nut" n="01">
				<frame>X=N0-이 V</frame>
				<subsense>
					<sel_rst arg="X" tht="THM">(입|입술)</sel_rst>
					<eg>할아버지의 입술은 계속해서 우물거리고 있었으나 가족들은 알아들을 수가 없어 너무나 답답했다.</eg>
				</subsense>
			</frame_grp>
		</sense>
	</entry>
	<entry n="2" pos="vv">
		<mnt_grp>
			<cre>
				<cre_date>2002/06/15</cre_date>
				<cre_writer>노윤채</cre_writer>
			</cre>
			<mod>
				<mod_date>2002/10/14</mod_date>
				<mod_writer>김종명</mod_writer>
			</mod>
			<mod>
				<mod_date>2003/07/18</mod_date>
				<mod_writer>노윤채</mod_writer>
			</mod>
			<mod>
				<mod_date>2004/12/16</mod_date>
				<mod_writer>한선혜</mod_writer>
			</mod>
		</mnt_grp>
		<morph_grp>
			<var type="lng">우물쩍거리다</var>
			<cntr opt="obl" type="i"/>
			<str>I.거</str>
			<infl type="reg"/>
		</morph_grp>
		<sense>
			<sem_grp>
				<sem_class>행위</sem_class>
				<trans>hesitate</trans>
			</sem_grp>
			<frame_grp type="FIN">
				<frame>X=N0-이 V</frame>
				<subsense>
					<sel_rst arg="X" tht="AGT">인간</sel_rst>
					<eg>우물거리지 말고 빨리 이야기해 봐.</eg>
					<eg>그 선수는 골 문 앞에만 가면 우물거리다가 항상 기회를 놓친다.</eg>
				</subsense>
			</frame_grp>
		</sense>
	</entry>
</superEntry>
