<?xml version="1.0" encoding="euc-kr" standalone="no"?>
<!DOCTYPE superEntry SYSTEM "vv.dtd">
<superEntry>
	<orth>인계되다</orth>
	<entry pos="vv">
		<mnt_grp>
			<cre>
				<cre_date>2006/07/12</cre_date>
				<cre_writer>안소진</cre_writer>
			</cre>
			<mod>
				<mod_date></mod_date>
				<mod_writer></mod_writer>
			</mod>
		</mnt_grp>
		<morph_grp>
			<var type="spr">인계가 되다</var>
			<str>N.되</str>
			<org lg="si">引繼_</org>
		</morph_grp>
		<sense>
			<sem_grp>
				<sem_class>피동적행위</sem_class>
				<trans></trans>
			</sem_grp>
			<frame_grp type="FIN">
				<frame>X=N0-이 Y=N1-에게|로 V</frame>
				<subsense>
					<sel_rst arg="X" tht="THM">구체물</sel_rst>
					<sel_rst arg="Y" tht="GOL">인간|인간집단</sel_rst>
					<eg>그는 담당부서로 인계되어 처벌을 받았다.</eg>
				</subsense>
				<subsense>
					<sel_rst arg="X" tht="THM">추상적대상</sel_rst>
					<sel_rst arg="Y" tht="GOL">인간|인간집단</sel_rst>
					<eg>회장의 모든 사업은 아들에게 인계되었다.</eg>
				</subsense>
			</frame_grp>
		</sense>
	</entry>
</superEntry>
