<?xml version="1.0" encoding="euc-kr" standalone="no"?>
<!DOCTYPE superEntry SYSTEM "vv.dtd">
<superEntry>
	<orth>호환되다</orth>
	<entry pos="vv">
		<mnt_grp>
			<cre>
				<cre_date>2003/09/28</cre_date>
				<cre_writer>허용</cre_writer>
				<cre_writer>유경민</cre_writer>
			</cre>
			<mod>
				<mod_date>2006/11/05</mod_date>
				<mod_writer>한선혜</mod_writer>
			</mod>
		</mnt_grp>
		<morph_grp>
			<var type="spr">호환이 되다</var>
			<cntr opt="opt" type="oi"/>
			<str>N.되</str>
			<org lg="si">互換_</org>
			<infl type="reg"/>
		</morph_grp>
		<sense>
			<sem_grp>
				<sem_class></sem_class>
				<trans>be interchanged</trans>
			</sem_grp>
			<frame_grp type="FIN" cor="sym" n="01">
				<frame>X=N0-이 Y=N1-와 (서로) V</frame>
				<subsense>
					<sel_rst arg="X" tht="THM">기구|기계|소프트웨어</sel_rst>
					<sel_rst arg="Y" tht="COM">기구|기계|소프트웨어</sel_rst>
					<eg>이 프로그램은 전에 사용하던 모든 문서작성 프로그램과 호환되어 사용이 편리하다.</eg>
				</subsense>
			</frame_grp>
			<frame_grp type="FIN" cor="sym" n="01">
				<frame>X+Y=N0-이 (서로) V</frame>
				<subsense>
					<sel_rst arg="X" tht="THM">기구|기계|소프트웨어</sel_rst>
					<sel_rst arg="Y" tht="THM">기구|기계|소프트웨어</sel_rst>
					<eg>동일 회사의 제품들도 사양에 따라서는 서로 호환되지 않을 수 있다.</eg>
				</subsense>
			</frame_grp>
		</sense>
	</entry>
</superEntry>
