<?xml version="1.0" encoding="euc-kr" standalone="no"?>
<!DOCTYPE superEntry SYSTEM "2007nb.dtd">
<superEntry>
	<orth>형</orth>
	<entry pos="nb">
		<mnt_grp>
			<cre>
				<cre_date>2001/09/15</cre_date>
				<cre_writer>방성원</cre_writer>
			</cre>
			<mod>
				<mod_date>2002/05/17</mod_date>
				<mod_writer>호정은</mod_writer>
			</mod>
			<mod>
				<mod_date>2003/05/22</mod_date>
				<mod_writer>김종인</mod_writer>
			</mod>
			<note>필수성을 고려하여 synt_c 정보 수정, superEntry 통합(호정은,2002)</note>
		</mnt_grp>
		<morph_grp>
			<org lg="si">兄</org>
					<hom exist="yes"/>
		</morph_grp>
		<sense n="1">
			<sem_grp>
				<eg>김 ~, 오늘 저녁에 시간 있소?</eg>
				<lr>
					<rel>씨</rel>
				</lr>
			</sem_grp>
			<syn_grp>
				<pre_d yn="no"/>
				<pre_n>N</pre_n>
				<s_n yn="no"/>
			</syn_grp>
		</sense>
	</entry>
	<entry pos="nb">
		<mnt_grp>
			<cre>
				<cre_date>2001/09/15</cre_date>
				<cre_writer>방성원</cre_writer>
			</cre>
			<mod>
				<mod_date>2002/05/17</mod_date>
				<mod_writer>호정은</mod_writer>
			</mod>
			<mod>
				<mod_date>2003/05/22</mod_date>
				<mod_writer>김종인</mod_writer>
			</mod>
			<note>필수성을 고려하여 synt_c 정보 수정(호정은,2002)</note>
		</mnt_grp>
		<morph_grp>
			<org lg="si">型</org>
					<hom exist="yes"/>
			<comp pos="n" type="prefix">천재~</comp>
			<comp pos="n" type="prefix">수재~</comp>
			<comp pos="n" type="prefix">순종~</comp>
			<comp pos="n" type="prefix">복종~</comp>
			<comp pos="n" type="prefix">권력~</comp>
			<comp pos="n" type="prefix">미인~</comp>
		</morph_grp>
		<sense n="1">
			<sem_grp>
				<eg>그는 권력을 좇는 ~이다</eg>
				<eg>나는 복스러운 ~의 여자가 좋더라</eg>
			</sem_grp>
			<syn_grp>
				<pre_d yn="no"/>
				<pre_n>N</pre_n>
				<s_n>S는 ~</s_n>
				<s_n>S은 ~</s_n>
				<s_n>S었을 ~</s_n>
				<s_n>S을 ~</s_n>
			</syn_grp>
		</sense>
	</entry>
	<entry pos="nb">
		<mnt_grp>
			<cre>
				<cre_date>2001/09/15</cre_date>
				<cre_writer>방성원</cre_writer>
			</cre>
			<mod>
				<mod_date>2002/05/17</mod_date>
				<mod_writer>호정은</mod_writer>
			</mod>
			<mod>
				<mod_date>2003/05/22</mod_date>
				<mod_writer>김종인</mod_writer>
			</mod>
			<note>필수성을 고려하여 synt_c 정보 수정(호정은,2002)</note>
		</mnt_grp>
		<morph_grp>
			<org lg="si">形</org>
					<hom exist="yes"/>
			<comp pos="n" type="prefix">직선~</comp>
			<comp pos="n" type="prefix">격자~</comp>
			<comp pos="n" type="prefix">나선~</comp>
			<comp pos="n" type="prefix">계란~</comp>
			<comp pos="n" type="prefix">원~</comp>
			<comp pos="n" type="prefix">타원~</comp>
		</morph_grp>
		<sense n="1">
			<sem_grp>
				<eg>팔 자 ~으로 걷는 사람은 신발 뒤축의 닳은 모양으로 표시가 난다</eg>
			</sem_grp>
			<syn_grp>
				<pre_d yn="no"/>
				<pre_n>N</pre_n>
				<s_n yn="no"/>
			</syn_grp>
		</sense>
	</entry>
</superEntry>
