<?xml version="1.0" encoding="euc-kr" standalone="no"?>
<!DOCTYPE superEntry SYSTEM "2007nn.dtd">
<superEntry>
	<orth>굴뚝산업</orth>
	<entry pos="nng_c">
		<mnt_grp>
			<cre>
				<cre_date>2004/09/20</cre_date>
				<cre_writer>김진형</cre_writer>
				<cre_note></cre_note>
			</cre>
			<mod>
				<mod_date>2004/0/</mod_date>
				<mod_writer>박진호</mod_writer>
				<mod_note></mod_note>
			</mod>
			<add></add>
		</mnt_grp>
		<see></see>
		<morph_grp>
			<var type="spr">굴뚝 산업</var>
			<str type="N_N">굴뚝+산업</str>
			<org lg="si">__産業</org>
		</morph_grp>
		<idm_grp>
			<idm type="etc"></idm>
		</idm_grp>
		<sense>
			<sem_grp>
				<eg>20세기 후반 들어 반도체 기술이 발달함에 따라 종래의 ~은 점차 비중이 약화되기 시작했다.</eg>
				<trans>smokestack industry</trans>
				<domain></domain>
				<sem_class>산업</sem_class>
				<lr>
					<syn type="etc"></syn> <!--중화학공업?-->
					<ant type="etc"></ant> <!--지식산업?-->
				</lr>
			</sem_grp>
			<syn_grp>
				<comb_aj type="appr"></comb_aj>
				<comb_n type="lexfunc"></comb_n>
				<comb_v type="narg_vpred">
					<form vcompound="no">~이 발달하다</form>
					<frame></frame>
				</comb_v>
				<comb_v type="narg_vpred">
					<form vcompound="no">~이 쇠퇴하다</form>
					<frame></frame>
				</comb_v>
				<max_n_str></max_n_str>
				<sel_rst arg="X"></sel_rst>
				<cl type="uni"></cl>
			</syn_grp>
		</sense>
	</entry>
</superEntry>