<?xml version="1.0" encoding="euc-kr" standalone="no"?>
<!DOCTYPE superEntry SYSTEM "2007nn.dtd">
<superEntry>
	<orth>사법고시</orth>
	<entry pos="nng_c">
		<mnt_grp>
			<cre>
				<cre_date>2004/07/03</cre_date>
				<cre_writer>김성용</cre_writer>
				<cre_note></cre_note>
			</cre>
			<mod>
				<mod_date>2004/09/10</mod_date>
				<mod_writer>호정은</mod_writer>
				<mod_note>변이형 정보(띄어쓰기) 추가</mod_note>
				<mod_note>원어 정보 추가</mod_note>
				<mod_note>n_n 정보 추가</mod_note>
				<mod_note>n_v 정보 수정 및 추가</mod_note>
			</mod>
			<mod>
				<mod_date>2004/12/29</mod_date>
				<mod_writer>김미현</mod_writer>
				<mod_note>mod_note 기술방식 수정</mod_note>
			</mod>
			<mod>
				<mod_date>2007/08/05</mod_date>
				<mod_writer>고길수</mod_writer>
				<mod_note>'보다, 치르다'를 다시 기능동사로 수정;논항 의미부류 정보 추가</mod_note>
			</mod>
			<add></add>
		</mnt_grp>
		<see></see>
		<morph_grp>
			<var type="spr">사법 고시</var>
			<var type="abb">사시</var>
			<str type="N_N">사법+고시</str>
			<org lg="si">司法考試</org><!--김성용(2004/07/03)연세한국어사전에서 高試로 되어 있음, 아마도 고등고시의 준말로 쓴 것 같음, 무엇이 맞는지 확인 요망-->
			<org lg="si">司法高試</org>
		</morph_grp>
		<idm_grp>
			<idm type="etc"></idm>
		</idm_grp>
		<sense>
			<sem_grp>
				<eg>~에 합격하기 위해서 절에 들어가는 학생들이 많이 있다.</eg>
				<trans>judicial examination</trans>
				<domain></domain>
				<sem_class>시험</sem_class>
				<lr>
					<syn type="etc"></syn>
					<ant type="etc"></ant>
				</lr>
			</sem_grp>
			<syn_grp>
				<comb_aj type="magn">~이 어렵다</comb_aj>
				<comb_aj type="min">~이 쉽다</comb_aj>
				<comb_n type="compound">~ 공부</comb_n>
				<comb_v type="npred_vsupvar"> <!--(호정은) 'vsupvar'를 'vpred'로 고침-->
					<form vcompound="no">~를 보다</form>
					<frame>X-이 ~을 보다</frame>
				</comb_v>
				<comb_v type="npred_vsupvar">
					<form vcompound="no">~를 치르다</form>
					<frame>X-이 ~을 치르다</frame>
				</comb_v>
				<comb_v type="npred_vpred">
					<form vcompound="no">~에 합격하다</form>
					<frame></frame>
				</comb_v>
				<max_n_str></max_n_str>
				<sel_rst arg="X">인간</sel_rst>
				<cl type="uni">차</cl>
				<cl type="uni">차례</cl>
				<cl type="uni">번</cl>
				<cl type="uni">회</cl>
			</syn_grp>
		</sense>
	</entry>
</superEntry>