<?xml version="1.0" encoding="euc-kr" standalone="no"?>
<!DOCTYPE superEntry SYSTEM "vv.dtd">
<superEntry>
	<orth>후끈하다</orth>
	<entry pos="va">
		<mnt_grp>
			<cre>
				<cre_date>2004/07/08</cre_date>
				<cre_writer>임유종</cre_writer>
			</cre>
			<mod>
				<mod_date>2004/10/10</mod_date>
				<mod_writer>한선혜</mod_writer>
			</mod>
			<mod>
				<mod_date>2006/09/25</mod_date>
				<mod_writer>한선혜</mod_writer>
			</mod>
		</mnt_grp>
		<morph_grp>
			<var type="etc">화끈하다</var>
			<str>D.하</str>
		</morph_grp>
		<sense>
			<sem_grp>
				<sem_class></sem_class>
				<trans>be hot</trans>
			</sem_grp>
			<frame_grp type="FA">
				<frame>X=N0-이 A</frame>
				<subsense>
					<sel_rst arg="X" tht="THM">구체물|장소|연기|바람|기운</sel_rst>
					<eg>목욕탕 문을 여니 후끈한 열기가 몸을 덮쳤다.</eg>
					<eg>얼마나 불을 땠던지 아직도 방바닥이 후끈하다.</eg>
				</subsense>
			</frame_grp>
		</sense>
	</entry>
</superEntry>
