<?xml version="1.0" encoding="euc-kr" standalone="no"?>
<!DOCTYPE superEntry SYSTEM "2007eomi.dtd">
<superEntry>
	<orth>마</orth>
	<entry n="1" pos="e">
		<mnt_grp>

			<cre>
				<cre_date>2001/07/05</cre_date>
				<cre_writer>이지영</cre_writer>
				<cre_note></cre_note>
			</cre>
			<mod>
				<mod_date>2001/09/15</mod_date>
				<mod_writer>이지영;이광호</mod_writer>
				<mod_note></mod_note>
			</mod>
			<mod>
				<mod_date>2003/08/12</mod_date>
				<mod_writer>김진형</mod_writer>
				<mod_note></mod_note>
			</mod>
			<mod>
				<mod_date>2006/11/12</mod_date>
				<mod_writer>하신영</mod_writer>
				<mod_note></mod_note>
			</mod>
			<mod>
				<mod_date>2007/07/08</mod_date>
				<mod_writer>하신영</mod_writer>
				<mod_note></mod_note>
			</mod>
		</mnt_grp>
		<head_grp>
			<je_subtype>eft</je_subtype>
		</head_grp>
		<morph_grp>
			<phn_rst>vo</phn_rst>
			<mor_rst>nil</mor_rst>
			<str></str>
			<var type="phn">으마</var>
		</morph_grp>
		<sem_grp>
			<sense n="1">
				<sem_rep>
					<st>평서</st>
					<sl>해라체</sl>
					<gm>약속</gm>
				</sem_rep>
				<frn></frn>
				<fol></fol>
				<frame>Vv-E</frame>
				<sel_rst></sel_rst>
				<own_s>
					<nc></nc>
					<sp>1인칭</sp>
				</own_s>
				<fol_s>
					<stt></stt>
					<prd></prd>
					<rep></rep>
					<sms></sms>
				</fol_s>
				<eg>어제 말했던 대로 내가 그 일을 하마.</eg>
			</sense>
		</sem_grp>
		<idm_grp>
			
				<idm></idm>
				<idm_eg></idm_eg>
			
		</idm_grp>
	</entry>
	<entry n="2" pos="e">
		<mnt_grp>

			<cre>
				<cre_date>2001/07/05</cre_date>
				<cre_writer>이지영</cre_writer>
				<cre_note></cre_note>
			</cre>
			<mod>
				<mod_date>2001/09/15</mod_date>
				<mod_writer>이지영;이광호</mod_writer>
				<mod_note></mod_note>
			</mod>
			<mod>
				<mod_date>2003/08/12</mod_date>
				<mod_writer>김진형</mod_writer>
				<mod_note></mod_note>
			</mod>
			<mod>
				<mod_date>2006/11/12</mod_date>
				<mod_writer>하신영</mod_writer>
				<mod_note></mod_note>
			</mod>
			<mod>
				<mod_date>2007/07/08</mod_date>
				<mod_writer>하신영</mod_writer>
				<mod_note></mod_note>
			</mod>
		</mnt_grp>
		<head_grp>
			<je_subtype>eft</je_subtype>
		</head_grp>
		<morph_grp>
			<phn_rst>vo</phn_rst>
			<mor_rst>nil</mor_rst>
			<str></str>
			<var type="phn">으마</var>
		</morph_grp>
		<sem_grp>
			<sense n="1">
				<sem_rep>
					<st>평서</st>
					<sl>완형보문</sl>
					<gm>약속</gm>
				</sem_rep>
				<frn></frn>
				<fol>고</fol>
				<frame>Vv-E</frame>
				<sel_rst></sel_rst>
				<own_s>
					<nc></nc>
					<sp></sp>
				</own_s>
				<fol_s>
					<stt></stt>
					<prd></prd>
					<rep></rep>
					<sms></sms>
				</fol_s>
				<eg>해 지기 전까지 돌아가마고 약속했지만 그는 오지 않았다.</eg>
				<eg>술만 먹으면 그러마 약속하고선 술만 깨면 언제 그랬냐는 식이지.</eg>
			</sense>
		</sem_grp>
		<idm_grp>
			
				<idm></idm>
				<idm_eg></idm_eg>
			
		</idm_grp>
	</entry>
</superEntry>
