<?xml version="1.0" encoding="euc-kr" standalone="no"?>
<!DOCTYPE superEntry SYSTEM "2007pron.dtd">
<superEntry>
	<orth>사형</orth>
	<entry pos="np">
		<mnt_grp>
			<cre>
				<cre_date>2001/07/22</cre_date>
				<cre_writer>호정은</cre_writer>
			</cre>
			<mod>
				<mod_date>2001/07/24</mod_date>
				<mod_writer>호정은</mod_writer>
			</mod>
			<mod>
				<mod_date>2003/06/30</mod_date>
				<mod_writer>김종인</mod_writer>
			</mod>
		</mnt_grp>
		<morph_grp>
			<org lg="si">師兄</org>
					<hom exist="yes"/>
		</morph_grp>
		<sense n="1" sem="2" num="singular" ref="human">
			<sem_grp>
				<eg>~께서는 먼 길에 피곤하실 테니 오늘은 일찍 쉬시지요</eg>
				<reg>존칭</reg>
				 
			</sem_grp>
			<syn_grp>
				<pre_d yn="no"/>
				<pre_n yn="no"/>
			</syn_grp>
		</sense>
	</entry>
</superEntry>
