<?xml version="1.0" encoding="euc-kr" standalone="no"?>
<!DOCTYPE superEntry SYSTEM "dic_adverb.dtd">
<superEntry>
	<orth>되게</orth>
	<entry n="1" pos="av">
		
		<mnt_grp>
			<cre>
				<cre_writer>김태경; 임유종; 남승호</cre_writer>
				<cre_date>2001/06/12</cre_date>
				<cre_note></cre_note>
			</cre>
			<mod>
				<mod_date>2001/09/22</mod_date>
			</mod>
			<note></note>
			<see></see>
		</mnt_grp>
		<morph_grp>
			<var type="xs"></var>
			<var type="xd"></var>
			<var type="xx"></var>
			<str>되-게</str>
			<org lg="temp"></org>
			<hom exist="temp"></hom>
		</morph_grp>
		<idm_grp>
		</idm_grp>
		<sense n="1">
			<sem_grp>
				<eg>이 영화 ~ 재미있다</eg>
				<trans>extremely</trans>
				<domain></domain>
				<reg>속어</reg>
				<con></con>
				
				<sem_rep>성분부사/정도부사/강도</sem_rep>
				<lr>
					<syn>엄청</syn>
					<syn>몹시</syn>
					<ant></ant>
					<hyper></hyper>
					<cohyp></cohyp>
					<hypo></hypo>
					<holo></holo>
					<mero></mero>
					<rel></rel>
				</lr>
			</sem_grp>
			<syn_grp>
				<comb pos="v" exist="yes">~앓다</comb>
				<comb pos="v" exist="yes">~자랑하다</comb>
				<comb pos="adj" exist="yes">~예쁘다</comb>
				<comb pos="det" exist="yes">~새</comb>
				<comb pos="av" exist="yes">~오래</comb>
				<comb pos="av" exist="yes">~가끔</comb>
				<comb pos="av" exist="yes">~잘</comb>
				<comb pos="n" exist="yes">~부자</comb>
				<prt>~도</prt>
				<argdist type="np"></argdist>
				<argdist type="vp"></argdist>
				<argdist type="ap"></argdist>
				<col></col>
			
			
				<conc type="conj"></conc>
				<conc type="mood"></conc>
				<conc type="mod"></conc>
				<conc type="ta"></conc>
				<conc type="neg"></conc>
				<conc type="agr"></conc>
				<distr>SO~V</distr>
			</syn_grp>
		</sense>
	</entry>
</superEntry>
