<?xml version="1.0" encoding="euc-kr" standalone="no"?>
<!DOCTYPE superEntry SYSTEM "dic_adverb.dtd">
<superEntry>
	<orth>모두</orth>
	<entry n="1" pos="av">
		
		<mnt_grp>
			<cre>
				<cre_writer>김태경</cre_writer>
				<cre_date>2000/08/10</cre_date>
				<cre_note></cre_note>
			</cre>
			<note></note>
			<see></see>
		</mnt_grp>
		<morph_grp>
			<var type="xs"></var>
			<var type="xd"></var>
			<var type="xx"></var>
			<org lg="temp"></org>
			<hom exist="yes"></hom>
		</morph_grp>
		<idm_grp>
		</idm_grp>
		<sense n="1">
			<sem_grp>
				<eg>결국 공교육이나 사교육 ~ 입시만을 위해 매진하고 있다</eg>
				<trans>all</trans>
				<domain></domain>
				<reg></reg>
				<con></con>
				
				<sem_rep>성분부사/정도부사/수량</sem_rep>
				<lr>
					<syn>전부</syn>
					<syn>다</syn>
					<syn>모조리</syn>
					<ant></ant>
					<hyper></hyper>
					<cohyp></cohyp>
					<hypo></hypo>
					<holo></holo>
					<mero></mero>
					<rel></rel>
				</lr>
			</sem_grp>
			<syn_grp>
				<comb pos="v" exist="yes">~뛰다</comb>
				<comb pos="adj" exist="yes">~예쁘다</comb>
				<comb pos="det" exist="temp"></comb>
				<comb pos="av" exist="yes">~다</comb>
				<comb pos="av" exist="yes">거의~</comb>
				<comb pos="n" exist="yes">~학생</comb>
				<prt></prt>
				<argdist type="np"></argdist>
				<argdist type="vp"></argdist>
				<argdist type="ap"></argdist>
				<col></col>
			
			
				<conc type="conj"></conc>
				<conc type="mood"></conc>
				<conc type="mod"></conc>
				<conc type="ta"></conc>
				<conc type="neg"></conc>
				<conc type="agr"></conc>
				<distr>SO~V</distr>
			</syn_grp>
		</sense>
		<sense n="2">
			<sem_grp>
				<eg>나는 하루에 한 켤레씩 신을 요량으로 ~ 일곱 켤레의 똑같은 색 양말을 구입했다</eg>
				<trans>in all</trans>
				<domain></domain>
				<reg></reg>
				<con></con>
				
				<sem_rep>성분부사/정도부사/수량</sem_rep>
				<lr>
					<syn>전부</syn>
					<syn>도합</syn>
					<ant></ant>
					<hyper></hyper>
					<cohyp></cohyp>
					<hypo></hypo>
					<holo></holo>
					<mero></mero>
					<rel></rel>
				</lr>
			</sem_grp>
			<syn_grp>
				<comb pos="v" exist="no"/>
				<comb pos="adj" exist="no"/>
				<comb pos="det" exist="yes">~몇</comb>
				<comb pos="av" exist="no"/>
				<comb pos="n" exist="no"/>
				<prt></prt>
				<argdist type="np"></argdist>
				<argdist type="vp"></argdist>
				<argdist type="ap"></argdist>
				<col></col>
			
			
				<conc type="conj"></conc>
				<conc type="mood"></conc>
				<conc type="mod"></conc>
				<conc type="ta"></conc>
				<conc type="neg"></conc>
				<conc type="agr"></conc>
				<distr>SO~V</distr>
			</syn_grp>
		</sense>
	</entry>
</superEntry>
