<?xml version="1.0" encoding="euc-kr" standalone="no"?>
<!DOCTYPE superEntry SYSTEM "dic_adverb.dtd">
<superEntry>
	<orth>소리소문없이</orth>
	<entry n="1" pos="av">
		
		<mnt_grp>
			<cre>
				<cre_writer>류병률; 남승호</cre_writer>
				<cre_date>2001/07/01</cre_date>
				<cre_note></cre_note>
			</cre>
			<mod>
				<mod_date>2001/09/08</mod_date>
			</mod>
			<note></note>
			<see></see>
		</mnt_grp>
		<morph_grp>
			<var type="xs"></var>
			<var type="xd"></var>
			<var type="xx"></var>
			<var type="abb">소리없이</var>
			<str>소리.소문+없이</str>
			<org lg="si">__所聞__</org>
			<hom exist="temp"></hom>
		</morph_grp>
		<idm_grp>
		</idm_grp>
		<sense n="1">
			<sem_grp>
				<eg>'좋은 생각'이라는 잡지가 ~ 창간됐다</eg>
				<eg>78세의 노령에도 불구하고 ~ 여덟번째 딸을 얻어 팬들을 놀라게 했다</eg>
				<eg>가까운 사람에게 단지 엽서 한장만으로 ~ 개업식을 대신하는 것이 보통이다</eg>
				<trans>without notice</trans>
				<domain></domain>
				<reg></reg>
				<con></con>
				
				<sem_rep>성분부사/양태부사/방식</sem_rep>
				<lr>
					<syn>통보없이</syn>
					<ant>시끌벅쩍하게</ant>
					<hyper></hyper>
					<cohyp></cohyp>
					<hypo></hypo>
					<holo></holo>
					<mero></mero>
					<rel></rel>
				</lr>
			</sem_grp>
			<syn_grp>
				<comb pos="v" exist="yes">~오다</comb>
				<comb pos="adj" exist="no"/>
				<comb pos="det" exist="temp"></comb>
				<comb pos="av" exist="temp"></comb>
				<comb pos="n" exist="temp"></comb>
				<prt></prt>
				<argdist type="np"></argdist>
				<argdist type="vp"></argdist>
				<argdist type="ap"></argdist>
				<col></col>
			
			
				<conc type="conj"></conc>
				<conc type="mood"></conc>
				<conc type="mod"></conc>
				<conc type="ta"></conc>
				<conc type="neg"></conc>
				<conc type="agr"></conc>
				<distr>S~O~V</distr>
			</syn_grp>
		</sense>
	</entry>
</superEntry>
