<?xml version="1.0" encoding="euc-kr" standalone="no"?>
<!DOCTYPE superEntry SYSTEM "dic_adverb.dtd">
<superEntry>
	<orth>움찔움찔</orth>
	<entry n="1" pos="av">
		
		<mnt_grp>
			<cre>
				<cre_writer>김선화; 임유종</cre_writer>
				<cre_date>2002/06/28</cre_date>
				<cre_note></cre_note>
			</cre>
			<mod>
				<mod_date>2002/07/04</mod_date>
			</mod>
			<note>의태, 중첩</note>
			<see></see>
		</mnt_grp>
		<morph_grp>
			<var type="xs"></var>
			<var type="xd"></var>
			<var type="xx"></var>
			<var type="abb">움찔</var>
			<str>움찔+움찔</str>
			<org lg="temp"></org>
			<hom exist="temp"></hom>
			<comp pos="v">~하다</comp>
			<img type="xt">움칠움칠</img>
			<img type="xc">옴찔옴찔</img>
		</morph_grp>
		<idm_grp>
		</idm_grp>
		<sense n="1">
			<sem_grp>
				<eg>아이는 침을 찌를 때마다 ~ 놀랐다</eg>
				<trans>frightened</trans>
				<domain></domain>
				<reg></reg>
				<con></con>
				
				<sem_rep>성분부사/양태부사/상징</sem_rep>
				<lr>
					<syn>깜짝깜짝</syn>
					<ant>평온하게</ant>
					<ant>평소와 다름없이</ant>
					<hyper></hyper>
					<cohyp></cohyp>
					<holo></holo>
					<mero></mero>
					<rel></rel>
				</lr>
			</sem_grp>
			<syn_grp>
				<comb pos="v" exist="yes">~놀라다</comb>
				<comb pos="v" exist="yes">~움직이다</comb>
				<comb pos="v" exist="yes">~움츠리다</comb>
				<comb pos="adj" exist="no"/>
				<comb pos="det" exist="temp"></comb>
				<comb pos="av" exist="temp"></comb>
				<comb pos="n" exist="temp"></comb>
				<prt></prt>
				<argdist type="np"></argdist>
				<argdist type="vp"></argdist>
				<argdist type="ap"></argdist>
				<col>~놀라다</col>
			
			
				<conc type="conj"></conc>
				<conc type="mood"></conc>
				<conc type="mod"></conc>
				<conc type="ta"></conc>
				<conc type="neg"></conc>
				<conc type="agr"></conc>
				<distr>SO~V</distr>
			</syn_grp>
		</sense>
	</entry>
	<entry n="2" pos="av">
		
		<mnt_grp>
			<cre>
				<cre_writer>김선화; 임유종</cre_writer>
				<cre_date>2002/06/28</cre_date>
				<cre_note></cre_note>
			</cre>
			<mod>
				<mod_date>2002/07/04</mod_date>
			</mod>
			<note>의태, 중첩</note>
			<see></see>
		</mnt_grp>
		<morph_grp>
			<var type="xs"></var>
			<var type="xd"></var>
			<var type="xx"></var>
			<var type="abb">움찔</var>
			<str>움찔+움찔</str>
			<org lg="temp"></org>
			<hom exist="temp"></hom>
			<comp pos="v">~하다</comp>
			<img type="xl">움질움질</img>
		</morph_grp>
		<idm_grp>
		</idm_grp>
		<sense n="1">
			<sem_grp>
				<eg>누군가가 문고리를 ~ 건드리는것 같았다</eg>
				<trans>wriggling</trans>
				<trans>slowly</trans>
				<domain></domain>
				<reg></reg>
				<con></con>
				
				<sem_rep>성분부사/양태부사/상징</sem_rep>
				<lr>
					<syn>느리게</syn>
					<syn>굼뜨게</syn>
					<ant>절도있게</ant>
					<hyper></hyper>
					<cohyp></cohyp>
					<holo></holo>
					<mero></mero>
					<rel></rel>
				</lr>
			</sem_grp>
			<syn_grp>
				<comb pos="v" exist="yes">~움직이다</comb>
				<comb pos="adj" exist="no"/>
				<comb pos="det" exist="temp"></comb>
				<comb pos="av" exist="temp"></comb>
				<comb pos="n" exist="temp"></comb>
				<prt></prt>
				<argdist type="np"></argdist>
				<argdist type="vp"></argdist>
				<argdist type="ap"></argdist>
				<col>~움직이다</col>
			
			
				<conc type="conj"></conc>
				<conc type="mood"></conc>
				<conc type="mod"></conc>
				<conc type="ta"></conc>
				<conc type="neg"></conc>
				<conc type="agr"></conc>
				<distr>SO~V</distr>
			</syn_grp>
		</sense>
		<sense n="2">
			<sem_grp>
				<eg>그는 결정적인 순간에 ~ 말하는 것을 망설였다</eg>
				<trans>irresolutely</trans>
				<domain></domain>
				<reg></reg>
				<con></con>
				
				<sem_rep>성분부사/양태부사/상징</sem_rep>
				<lr>
					<syn>주저주저</syn>
					<syn>망설이며</syn>
					<ant>단호히</ant>
					<hyper></hyper>
					<cohyp></cohyp>
					<holo></holo>
					<mero></mero>
					<rel></rel>
				</lr>
			</sem_grp>
			<syn_grp>
				<comb pos="v" exist="yes">~망설이다</comb>
				<comb pos="v" exist="yes">~주저하다</comb>
				<comb pos="adj" exist="no"/>
				<comb pos="det" exist="temp"></comb>
				<comb pos="av" exist="temp"></comb>

				<comb pos="n" exist="temp"></comb>
				<prt></prt>
				<argdist type="np"></argdist>
				<argdist type="vp"></argdist>
				<argdist type="ap"></argdist>
				<col>~망설이다</col>
			
			
				<conc type="conj"></conc>
				<conc type="mood"></conc>
				<conc type="mod"></conc>
				<conc type="ta"></conc>
				<conc type="neg"></conc>
				<conc type="agr"></conc>
				<distr>SO~V</distr>
			</syn_grp>
		</sense>
	</entry>
</superEntry>
