<?xml version="1.0" encoding="euc-kr" standalone="no"?>
<!DOCTYPE superEntry SYSTEM "dic_adverb.dtd">
<superEntry>
	<orth>절렁</orth>
	<entry n="1" pos="av">
		
		<mnt_grp>
			<cre>
				<cre_writer>김선화; 임유종</cre_writer>
				<cre_date>2002/07/16</cre_date>
				<cre_note></cre_note>
			</cre>
			<note>의성</note>
			<see></see>
		</mnt_grp>
		<morph_grp>
			<var type="xs"></var>
			<var type="xd"></var>
			<var type="xx"></var>
			<org lg="temp"></org>
			<hom exist="temp"></hom>
			<der pos="v">~거리다</der>
			<der pos="v">~대다</der>
			<der pos="v">~이다</der>
			<comp pos="v">~하다</comp>
			<metc>절렁절렁</metc>
			<img type="xt">쩔렁</img>
			<img type="xt">철렁</img>
			<img type="xc">잘랑</img>
		</morph_grp>
		<idm_grp>
		</idm_grp>
		<sense n="1">
			<sem_grp>
				<eg>주머니 속의 동전들을 손으로 ~ 흔들었다</eg>
				<trans>with a clink</trans>
				<domain></domain>
				<reg></reg>
				<con></con>
				
				<sem_rep>성분부사/양태부사/상징</sem_rep>
				<lr>
					<syn>절그렁</syn>
					<syn>쇠붙이가 부딪치는 소리</syn>
					<ant>조용히</ant>
					<ant>철커덕</ant>
					<hyper></hyper>
					<cohyp></cohyp>
					<holo></holo>
					<mero></mero>
					<rel></rel>
				</lr>
			</sem_grp>
			<syn_grp>
				<comb pos="v" exist="yes">~흔들리다</comb>
				<comb pos="v" exist="yes">~부딪치다</comb>
				<comb pos="v" exist="yes">~소리나다</comb>
				<comb pos="adj" exist="no"/>
				<comb pos="det" exist="temp"></comb>
				<comb pos="av" exist="temp"></comb>
				<comb pos="n" exist="temp"></comb>
				<prt></prt>
				<argdist type="np"></argdist>
				<argdist type="vp"></argdist>
				<argdist type="ap"></argdist>
				<col>~소리나다</col>
			
			
				<conc type="conj"></conc>
				<conc type="mood"></conc>
				<conc type="mod"></conc>
				<conc type="ta"></conc>
				<conc type="neg"></conc>
				<conc type="agr"></conc>
				<distr>SO~V</distr>
			</syn_grp>
		</sense>
	</entry>
</superEntry>
