<?xml version="1.0" encoding="euc-kr" standalone="no"?>
<!DOCTYPE superEntry SYSTEM "dic_adverb.dtd">
<superEntry>
	<orth>참</orth>
	<entry n="1" pos="av">
		
		<mnt_grp>
			<cre>
				<cre_writer>김태경</cre_writer>
				<cre_date>2000/08/14</cre_date>
				<cre_note></cre_note>
			</cre>
			<note></note>
			<see></see>
		</mnt_grp>
		<morph_grp>
			<var type="xs"></var>
			<var type="xd"></var>
			<var type="xx"></var>
			<org lg="temp"></org>
			<hom exist="yes"></hom>
			<der pos="av">~으로</der>
			<comp pos="av">~말</comp>
		</morph_grp>
		<idm_grp>
		</idm_grp>
		<sense n="1">
			<sem_grp>
				<eg>저녁 노을이 ~ 멋있다</eg>
				<trans>indeed</trans>
				<domain></domain>
				<reg></reg>
				<con></con>
				
				<sem_rep>성분부사/정도부사/강도</sem_rep>
				<lr>
					<syn>정말</syn>
					<ant></ant>
					<hyper></hyper>
					<cohyp></cohyp>
					<hypo></hypo>
					<holo></holo>
					<mero></mero>
					<rel>실로</rel>
				</lr>
			</sem_grp>
			<syn_grp>
				<comb pos="v" exist="yes">~좋아하다</comb>
				<comb pos="adj" exist="yes">~예쁘다</comb>
				<comb pos="det" exist="yes">~새</comb>
				<comb pos="av" exist="yes">~자주</comb>
				<comb pos="av" exist="yes">~많이</comb>
				<comb pos="av" exist="yes">~잘</comb>
				<comb pos="n" exist="yes">~비극</comb>
				<prt></prt>
				<argdist type="np"></argdist>
				<argdist type="vp"></argdist>
				<argdist type="ap"></argdist>
				<col></col>
			
			
				<conc type="conj"></conc>
				<conc type="mood">~-(는)다</conc>
				<conc type="mood">~-(는)구나</conc>
				<conc type="mod"></conc>
				<conc type="ta"></conc>
				<conc type="neg"></conc>
				<conc type="agr"></conc>
				<distr>~S~O~V</distr>
			</syn_grp>
		</sense>
	</entry>
</superEntry>
